.gitignore
.travis.yml
CHANGES.rst
MANIFEST.in
README.rst
bootstrap.py
buildout.cfg
setup.py
src/initgroups/__init__.py
src/initgroups.egg-info/PKG-INFO
src/initgroups.egg-info/SOURCES.txt
src/initgroups.egg-info/dependency_links.txt
src/initgroups.egg-info/top_level.txt
src/initgroups.egg-info/zip-safe