Metadata-Version: 1.1
Name: initgroups
Version: 4.0
Summary: Convenience uid/gid helper function used in Zope2.
Home-page: https://github.com/zopefoundation/initgroups
Author: Zope Corporation and Contributors
Author-email: zope-dev@zope.org
License: ZPL 2.1
Keywords: deprecated,uid,gid,Zope2
Platform: UNKNOWN
Classifier: Development Status :: 7 - Inactive
Classifier: Framework :: Zope2
Classifier: License :: OSI Approved :: Zope Public License
Classifier: Operating System :: OS Independent
Classifier: Programming Language :: Python
Classifier: Programming Language :: Python :: 2
Classifier: Programming Language :: Python :: 2.7
Classifier: Programming Language :: Python :: Implementation :: CPython
